metric_logger/__init__.py
metric_logger/logger.py
metric_logger-0.5.dist-info/LICENSE
metric_logger-0.5.dist-info/METADATA
metric_logger-0.5.dist-info/WHEEL
metric_logger-0.5.dist-info/top_level.txt
metric_logger-0.5.dist-info/RECORD
