Metadata-Version: 2.1
Name: metric-logger
Version: 0.5
Summary: Simple Metric logger.
Home-page: https://github.com/darkhan-ai/metric-logger
License: MIT
License-File: LICENSE
